ndev_settings/__init__.py
ndev_settings/_settings.py
ndev_settings/_settings_widget.py
ndev_settings/_version.py
ndev_settings/napari.yaml
ndev_settings/ndev_settings.yaml
ndev_settings-0.2.0.dist-info/licenses/LICENSE
ndev_settings-0.2.0.dist-info/METADATA
ndev_settings-0.2.0.dist-info/WHEEL
ndev_settings-0.2.0.dist-info/entry_points.txt
ndev_settings-0.2.0.dist-info/top_level.txt
ndev_settings-0.2.0.dist-info/RECORD
