Metadata-Version: 2.4
Name: ndev-settings
Version: 0.2.0
Summary: Reusable settings and customization widget for the ndev-kit
Author: Tim Monko
Author-email: timmonko@gmail.com
License: 
Project-URL: Bug Tracker, https://github.com/ndev-kit/ndev-settings/issues
Project-URL: Documentation, https://github.com/ndev-kit/ndev-settings#README.md
Project-URL: Source Code, https://github.com/ndev-kit/ndev-settings
Project-URL: User Support, https://github.com/ndev-kit/ndev-settings/issues
Classifier: Development Status :: 2 - Pre-Alpha
Classifier: Framework :: napari
Classifier: Intended Audience :: Developers
Classifier: License :: OSI Approved :: BSD License
Classifier: Operating System :: OS Independent
Classifier: Programming Language :: Python
Classifier: Programming Language :: Python :: 3
Classifier: Programming Language :: Python :: 3 :: Only
Classifier: Programming Language :: Python :: 3.10
Classifier: Programming Language :: Python :: 3.11
Classifier: Programming Language :: Python :: 3.12
Classifier: Programming Language :: Python :: 3.13
Classifier: Topic :: Scientific/Engineering :: Image Processing
Requires-Python: >=3.10
License-File: LICENSE
Requires-Dist: magicgui
Requires-Dist: magic-class
Requires-Dist: pyyaml
Provides-Extra: all
Requires-Dist: napari[all]; extra == "all"
Dynamic: license-file
